PyFina/PyFina.py
PyFina/__init__.py
PyFina/py.typed
PyFina-0.0.7.dist-info/LICENSE
PyFina-0.0.7.dist-info/METADATA
PyFina-0.0.7.dist-info/WHEEL
PyFina-0.0.7.dist-info/top_level.txt
PyFina-0.0.7.dist-info/RECORD
