Metadata-Version: 2.2
Name: PyFina
Version: 0.0.7
Summary: A numpy subclass to read emoncms PHPFINA feeds as numpy array
Home-page: https://github.com/Open-Building-Management/PyFina
Author: Alexandre CUER
Author-email: alexandre.cuer@wanadoo.fr
Project-URL: Bug Tracker, https://github.com/Open-Building-Management/PyFina/issues
Classifier: Programming Language :: Python :: 3
Classifier: License :: OSI Approved :: MIT License
Classifier: Operating System :: OS Independent
Requires-Python: >=3.6
License-File: LICENSE
Requires-Dist: numpy
Dynamic: author
Dynamic: author-email
Dynamic: classifier
Dynamic: description
Dynamic: description-content-type
Dynamic: home-page
Dynamic: project-url
Dynamic: requires-dist
Dynamic: requires-python
Dynamic: summary
